easy_multip/__init__.py
easy_multip/decorators.py
easy_multip/functions.py
easy_multip-0.3.4.dist-info/LICENSE.txt
easy_multip-0.3.4.dist-info/METADATA
easy_multip-0.3.4.dist-info/WHEEL
easy_multip-0.3.4.dist-info/top_level.txt
easy_multip-0.3.4.dist-info/RECORD
