Metadata-Version: 2.1
Name: easy-multip
Version: 0.3.4
Summary: Easy Python multiprocessing
Home-page: https://github.com/zachbateman/easy_multip.git
Author: Zach Bateman
License: MIT
Download-URL: https://github.com/zachbateman/easy_multip/archive/v_0.3.4.tar.gz
Keywords: MULTIPROCESSING,SIMPLE,EASY,PARALLEL
Platform: UNKNOWN
Classifier: Development Status :: 3 - Alpha
Classifier: License :: OSI Approved :: MIT License
Classifier: Programming Language :: Python :: 3
Classifier: Programming Language :: Python :: 3.6
Classifier: Programming Language :: Python :: 3.7
Classifier: Programming Language :: Python :: 3.8
Classifier: Programming Language :: Python :: 3.9
Classifier: Programming Language :: Python :: 3.10
Requires-Dist: tqdm
